Workbook
Name code2: [1]別紙１!#REF!
Name code2: [1]別紙１!#REF!
Name code2: [1]別紙１!#REF!
Name code2: [1]別紙１!#REF!
Name code2: [1]別紙１!#REF!
Name 別紙７: [2]別紙１!#REF!
Name 別紙７: [2]別紙１!#REF!
Name 別紙７: [2]別紙１!#REF!

Sheet 【記入例】履歴書
A2: 臨時職員採用履歴書
A3: ふりがな
A4: 氏 名
A6: 昭和・平成 | E6: 年 | J6: 月 | N6: 日生 | R6: （満 歳） | Z6: 性 別
A8: ふりがな | AE8: 電話：
A9: 現住所 | D9: 〒 | AE9: 携帯：
AE10: E-mail:
A11: ふりがな | AG11: 電話等：
A12: 連絡先 | D12: 〒 (現住所以外に連絡を希望する場合のみ記入)
A13: ※以下、いずれの欄も「年月日」はすべて 元号 にて記入すること。また、書ききれない場合は別紙（様式自由）を作成することも可。
D14: 自 | M14: 至 | W14: 学 | AB14: 歴
D15: 年 | F15: 月 | H15: 日 | I15: ～ | M15: 年 | O15: 月 | Q15: 日 | AJ15: 卒・修・中
D16: 年 | F16: 月 | H16: 日 | I16: ～ | M16: 年 | O16: 月 | Q16: 日 | AJ16: 卒・修・中
D17: 年 | F17: 月 | H17: 日 | I17: ～ | M17: 年 | O17: 月 | Q17: 日 | AJ17: 卒・修・中
D19: 自 | M19: 至 | R19: 職歴(公立大学法人首都大学東京以外における職歴)
D20: 年 | F20: 月 | H20: 日 | I20: ～ | M20: 年 | O20: 月 | Q20: 日
D21: 年 | F21: 月 | H21: 日 | I21: ～ | M21: 年 | O21: 月 | Q21: 日
D22: 年 | F22: 月 | H22: 日 | I22: ～ | M22: 年 | O22: 月 | Q22: 日
A24: 免許・資格・語学等 | P24: 職歴（法人における職歴） ※ 記載日時点で本契約の他に法人に対して、応募中のものや雇用契約を締結（予定も含む）しているものがあれば記入すること ※ 書ききれない場合は、別紙に記入すること
A25: 取得年月日 | H25: 免許・資格・試験名 | P25: 自～至 | Z25: 勤務所属（部局・課等） | AI25: 週当たり勤務日数
A26: 年 月 日 | T26: 年 | V26: 月 | X26: 日
P27: ～ | T27: 年 | V27: 月 | X27: 日
A28: 年 月 日 | T28: 年 | V28: 月 | X28: 日
P29: ～ | T29: 年 | V29: 月 | X29: 日
A30: 年 月 日 | T30: 年 | V30: 月 | X30: 日
P31: ～ | T31: 年 | V31: 月 | X31: 日
A32: 年 月 日 | T32: 年 | V32: 月 | X32: 日
P33: ～ | T33: 年 | V33: 月 | X33: 日
A34: 年 月 日 | T34: 年 | V34: 月 | X34: 日
P35: ～ | T35: 年 | V35: 月 | X35: 日
A37: 【志望動機及び実績・経験等】※書ききれない場合は、別紙に記入することも可
B42: 以上の記載事項はすべて真実であることを誓います。 | U42: ※日付及び氏名欄については、必ず自署してください。
D43: 年 月 日
AA45: 氏 名 | AL45: 印

Sheet 入力用　履歴書
A2: 臨時職員採用履歴書
A3: ふりがな
A4: 氏 名
A6: 昭和・平成 | E6: 年 | J6: 月 | N6: 日生 | R6: （満 歳） | Z6: 性 別
A8: ふりがな | AE8: 電話：
A9: 現住所 | D9: 〒 | AE9: 携帯：
AE10: E-mail:
A11: ふりがな | AG11: 電話等：
A12: 連絡先 | D12: 〒 (現住所以外に連絡を希望する場合のみ記入)
A13: ※以下、いずれの欄も「年月日」はすべて 元号 にて記入すること。また、書ききれない場合は別紙（様式自由）を作成することも可。
D14: 自 | M14: 至 | W14: 学 | AB14: 歴
D15: 年 | F15: 月 | H15: 日 | I15: ～ | M15: 年 | O15: 月 | Q15: 日 | AJ15: 卒・修・中
D16: 年 | F16: 月 | H16: 日 | I16: ～ | M16: 年 | O16: 月 | Q16: 日 | AJ16: 卒・修・中
D17: 年 | F17: 月 | H17: 日 | I17: ～ | M17: 年 | O17: 月 | Q17: 日 | AJ17: 卒・修・中
D19: 自 | M19: 至 | R19: 職歴(公立大学法人首都大学東京以外における職歴)
D20: 年 | F20: 月 | H20: 日 | I20: ～ | M20: 年 | O20: 月 | Q20: 日
D21: 年 | F21: 月 | H21: 日 | I21: ～ | M21: 年 | O21: 月 | Q21: 日
D22: 年 | F22: 月 | H22: 日 | I22: ～ | M22: 年 | O22: 月 | Q22: 日
A24: 免許・資格・語学等 | P24: 臨時職員の職歴（法人における職歴） ※書ききれない場合は、別紙に記入すること
A25: 取得年月日 | H25: 免許・資格・試験名 | P25: 自～至 | Z25: 勤務所属（部局・課等） | AI25: 週当たり勤務日数
A26: 年 月 日 | T26: 年 | V26: 月 | X26: 日
P27: ～ | T27: 年 | V27: 月 | X27: 日
A28: 年 月 日 | T28: 年 | V28: 月 | X28: 日
P29: ～ | T29: 年 | V29: 月 | X29: 日
A30: 年 月 日 | T30: 年 | V30: 月 | X30: 日
P31: ～ | T31: 年 | V31: 月 | X31: 日
A32: 年 月 日 | T32: 年 | V32: 月 | X32: 日
P33: ～ | T33: 年 | V33: 月 | X33: 日
A34: 年 月 日 | T34: 年 | V34: 月 | X34: 日
P35: ～ | T35: 年 | V35: 月 | X35: 日
A37: 【志望動機及び実績・経験等】※書ききれない場合は、別紙に記入することも可
B42: 以上の記載事項はすべて真実であることを誓います。 | U42: ※日付及び氏名欄については、必ず自署してください。
D43: 年 月 日
AA45: 氏 名 | AL45: 印

Sheet 別紙　履歴書(職歴)
A1: 【別紙】臨時職員採用履歴書
A2: 職歴（法人における職歴）
A3: 年 月 日現在
A4: ふりがな
A5: 氏 名
A7: 自～至 | C7: 勤務所属（部局・課等） | D7: 週当たり
D8: 勤務日数
A9: 年 月 日
A10: ～ 年 月 日
A11: 年 月 日
A12: ～ 年 月 日
A13: 年 月 日
A14: ～ 年 月 日
A15: 年 月 日
A16: ～ 年 月 日
A17: 年 月 日
A18: ～ 年 月 日
A19: 年 月 日
A20: ～ 年 月 日
... A48: ～ 年 月 日

Sheet 通勤届
A1: 通 勤 届（□新規・□変更）
A2: 年 月 日
A3: 公立大学法人
A4: 首都大学東京理事長 殿
A6: 下記のとおり届け出します。
C7: 所属
C8: 職 | D8: 臨時職員 | H8: 氏名 | Q8: 印
A11: 住所
A12: 通 勤 方 法 | B12: 自 宅 | F12: 徒歩 | G12: 交通用具名(距離) | K12: 交通機関路線名(乗車券種別) | O12: 金 額 | Q12: 備 考
F13: □ | G13: □ | K13: □
I15: （ ． ㎞） | L15: （ ） | O15: 円
F17: □ | G17: □ | K17: □
I19: （ ． ㎞） | L19: （ ） | O19: 円
F21: □ | G21: □ | K21: □
I23: （ ． ㎞） | L23: （ ） | O23: 円
F25: □ | G25: □ | K25: □
I27: （ ． ㎞） | L27: （ ） | O27: 円
F29: □ | G29: □ | K29: □
I31: （ ． ㎞） | L31: （ ） | O31: 円
F32: ※区間毎の通勤方法（徒歩、自転車、○○線等）を記入してください。 | O32: =SUM(O13:O29) -> 0
A34: 通勤経路（自宅→最寄駅）
B35: ※通勤経路を「→」で朱書きすること。
A36: 備考欄

Sheet 【記入例】通勤届.
A1: 通 勤 届（□新規・□変更）
A2: 年 月 日
A3: 公立大学法人
A4: 首都大学東京理事長 殿
A6: 下記のとおり届け出します。
C7: 所属 | D7: 首都大学東京 都市環境学部 〇〇学科
C8: 職 | D8: 臨時職員 | H8: 氏名 | J8: 首都大 花子 | Q8: 印
A11: 住所 | B11: 東京都荒川区南千住８－１７－１
A12: 通 勤 方 法 | B12: 自 宅 | F12: 徒歩 | G12: 交通用具名(距離) | K12: 交通機関路線名(乗車券種別) | O12: 金 額 | Q12: 備 考
F13: ■ | G13: □ | K13: □
B15: 南千住 | I15: （1．4㎞） | L15: （ ） | O15: 円
F17: □ | G17: □ | I17: 電車 | K17: □ | L17: JR常磐線 | O17: 210
B19: 日暮里 | I19: （3．4㎞） | L19: （普通運賃） | O19: 円
F21: □ | G21: □ | I21: 電車 | K21: □ | L21: JR山手線
B23: 新宿 | I23: （11．3㎞） | L23: （普通運賃） | O23: 円
F25: □ | G25: □ | I25: 電車 | K25: □ | L25: 京王線 | O25: 390
B27: 南大沢 | I27: （33．7㎞） | L27: （普通運賃） | O27: 円
F29: ■ | G29: □ | K29: □
B31: 首都大学東京 | I31: （0．8㎞） | L31: （ ） | O31: 円
F32: ※区間毎の通勤方法（徒歩、自転車、○○線等）を記入してください。 | O32: 合計 円
O33: 600
A34: 通勤経路（自宅→最寄駅）
B35: ※通勤経路を「→」で朱書きすること。
A36: 備考欄 ※通勤経路は、自宅付近から最寄駅までの地図を添付していただいても結構です。

Sheet 月額表（平成27年1月以降分）
B1: 給与所得の源泉徴収税額表（平成27年分）
B2: 月 額 表（平成24年３月31日財務省告示第115号別表第一（平成25年５月31日財務省告示第175号改正））
B3: その月の社会保 | D3: 甲
B4: 険料等控除後の | D4: 扶 養 親 族 等 の 数 | L4: 乙
B5: 給与等の金額 | D5: 0 人 | E5: 1 人 | F5: 2 人 | G5: 3 人 | H5: 4 人 | I5: 5 人 | J5: 6 人 | K5: 7 人
B6: 以 上 | C6: 未 満 | D6: 税 額 | L6: 税 額
B7: 円 | C7: 円 | D7: 円 | E7: 円 | F7: 円 | G7: 円 | H7: 円 | I7: 円 | J7: 円 | K7: 円 | L7: 円
B8: 88000 | C8: 円未満 | D8: 0 | E8: 0 | F8: 0 | G8: 0 | H8: 0 | I8: 0 | J8: 0 | K8: 0 | L8: その月の社会保険料等控除後の給与等の金額の3.063％に相当する金額
A10: 1 | B10: 88000 | C10: 89000 | D10: 130 | E10: 0 | F10: 0 | G10: 0 | H10: 0 | I10: 0 | J10: 0 | K10: 0 | L10: 3200
A11: 2 | B11: 89000 | C11: 90000 | D11: 180 | E11: 0 | F11: 0 | G11: 0 | H11: 0 | I11: 0 | J11: 0 | K11: 0 | L11: 3200
A12: 3 | B12: 90000 | C12: 91000 | D12: 230 | E12: 0 | F12: 0 | G12: 0 | H12: 0 | I12: 0 | J12: 0 | K12: 0 | L12: 3200
A13: 4 | B13: 91000 | C13: 92000 | D13: 290 | E13: 0 | F13: 0 | G13: 0 | H13: 0 | I13: 0 | J13: 0 | K13: 0 | L13: 3200
A14: 5 | B14: 92000 | C14: 93000 | D14: 340 | E14: 0 | F14: 0 | G14: 0 | H14: 0 | I14: 0 | J14: 0 | K14: 0 | L14: 3300
A16: 6 | B16: 93000 | C16: 94000 | D16: 390 | E16: 0 | F16: 0 | G16: 0 | H16: 0 | I16: 0 | J16: 0 | K16: 0 | L16: 3300
A17: 7 | B17: 94000 | C17: 95000 | D17: 440 | E17: 0 | F17: 0 | G17: 0 | H17: 0 | I17: 0 | J17: 0 | K17: 0 | L17: 3300
A18: 8 | B18: 95000 | C18: 96000 | D18: 490 | E18: 0 | F18: 0 | G18: 0 | H18: 0 | I18: 0 | J18: 0 | K18: 0 | L18: 3400
A19: 9 | B19: 96000 | C19: 97000 | D19: 540 | E19: 0 | F19: 0 | G19: 0 | H19: 0 | I19: 0 | J19: 0 | K19: 0 | L19: 3400
A20: 10 | B20: 97000 | C20: 98000 | D20: 590 | E20: 0 | F20: 0 | G20: 0 | H20: 0 | I20: 0 | J20: 0 | K20: 0 | L20: 3500
A22: 11 | B22: 98000 | C22: 99000 | D22: 640 | E22: 0 | F22: 0 | G22: 0 | H22: 0 | I22: 0 | J22: 0 | K22: 0 | L22: 3500
A23: 12 | B23: 99000 | C23: 101000 | D23: 720 | E23: 0 | F23: 0 | G23: 0 | H23: 0 | I23: 0 | J23: 0 | K23: 0 | L23: 3600
... A410: 335 | B410: 1007000 | C410: 1010000 | D410: 133710 | E410: 123040 | F410: 115290 | G410: 107860 | H410: 100430 | I410: 92980 | J410: 85550 | K410: 78610 | L410: 395100
B412: 1,010,000円 | D412: 134190 | E412: 123520 | F412: 115630 | G412: 108200 | H412: 100750 | I412: 93320 | J412: 85890 | K412: 78890 | L412: 396700
B415: 1,010,000円を超え | L415: 396,700円に、その月の社会保険料等控除後の給与等の金額のうち1,010,000円を超える金額の40.84％に相当する金額を加算した金額
D416: 1,010,000円の場合の税額に、その月の社会保険料等控除後の給与等の金額のうち
B418: 1,250,000円に満た
D419: 1,010,000円を超える金額の32.1615％に相当する金額を加算した金額
B421: ない金額
B424: 1,250,000円 | D424: 211380 | E424: 200710 | F424: 192820 | G424: 185390 | H424: 177940 | I424: 170510 | J424: 163080 | K424: 156080 | L424: 494800
B426: 1,250,000円を超え | L426: 494,800円に、その月の社会保険料等控除後の給与等の金額のうち1,250,000円を超える金額の45.945％に相当する金額を加算した金額
D427: 1,250,000円の場合の税額に、その月の社会保険料等控除後の給与等の金額のうち
B428: 1,740,000円に満た
D429: 1,250,000円を超える金額の33.693％に相当する金額を加算した金額
B430: ない金額
D432: 円 | E432: 円 | F432: 円 | G432: 円 | H432: 円 | I432: 円 | J432: 円 | K432: 円
B433: 1,740,000円 | D433: 376480 | E433: 365810 | F433: 357920 | G433: 350490 | H433: 343040 | I433: 335610 | J433: 328180 | K433: 321180
B435: 1,740,000円を超え
D436: 1,740,000円の場合の税額に、その月の社会保険料等控除後の給与等の金額のうち
B437: 3,570,000円に満た
D438: 1,740,000円を超える金額の40.84％に相当する金額を加算した金額
B439: ない金額
D441: 円 | E441: 円 | F441: 円 | G441: 円 | H441: 円 | I441: 円 | J441: 円 | K441: 円
B442: 3,570,000円 | D442: 1123860 | E442: 1113190 | F442: 1105300 | G442: 1097870 | H442: 1090420 | I442: 1082990 | J442: 1075560 | K442: 1068560
B444: 3,570,000円を超え | D444: 3,570,000円の場合の税額に、その月の社会保険料等控除後の給与等の金額のうち
B446: る金額 | D446: 3,570,000円を超える金額の45.945％に相当する金額を加算した金額
L449: 従たる給与についての扶養控除等申告書が提出されている場合には、当該申告書に記載された扶養親族等の数に応じ、扶養親族等１人ごとに1,610円を、上の各欄によって求めた税額から控除した金額
B451: 扶養親族等の数が7人を超える場合には、扶養親族等の数が7人の場合の税額から、その7人を超える
B455: １人ごとに1,610円を控除した金額
B461: (注) この表において「扶養親族等」とは、控除対象配偶者及び控除対象扶養親族をいいます。
B462: (備考） 税額の求め方は、次のとおりです。
B463: 1 「給与所得者の扶養控除等申告書」（以下この表において「扶養控除等申告書」といいます。）の提出があった人
B464: (1) まず、その人のその月の給与等の金額から、その給与等の金額から控除される社会保険料等の金額を控除した金額を求めます。
B465: (2) 次に、扶養控除等申告書により申告された扶養親族等の数が７人以下である場合には、(1)により求めた金額に応じて「その月の社会保険料等控除後
B466: の給与等の金額」欄の該当する行を求め、その行と扶養親族等の数に応じた甲欄の該当欄との交わるところに記載されている金額を求めます。これが
B467: 求める税額です。
B468: (3) 扶養控除等申告書により申告された扶養親族等の数が７人を超える場合には、(1)により求めた金額に応じて、扶養親族等の数が７人であるものと
B469: して(2)により求めた税額から、扶養親族等の数が７人を超える１人ごとに1,610円を控除した金額を求めます。これが求める税額です。
B470: (4) (2)及び(3)の場合において、扶養控除等申告書にその人が障害者（特別障害者を含みます。）、寡婦（特別の寡婦を含みます。）、寡夫又は勤労
... B477: 場合には、その申告書により申告された扶養親族等の数に応じ、扶養親族等１人ごとに1,610円を控除した金額）を求めます。これが求める税額です。

Sheet 事務室処理用　財務会計支払
F2: 勤務実績（年・月） | G2: 平成 | I2: 年 | K2: 月分 | M2: 4 | N2: 41730
F3: 通勤費用(片道) | M3: 5 | N3: 41760
F4: 勤務時間数 | M4: 6 | N4: 41791
F5: 勤務日数 | M5: 7 | N5: 41821
E6: その月の初日(一日）→ | F6: 契約日 | H6: =VLOOKUP(J2,M2:N13,2,0) -> #N/A | M6: 8 | N6: 41852
E7: その月の最終勤務日→ | F7: 伝票日付(勤務最終日） | M7: 9 | N7: 41883
F8: 支払予定日 | M8: 10 | N8: 41913
F9: 支払予定日（源泉分） | H9: =VLOOKUP(H8,M15:N40,2,0) -> #N/A | J9: =F20-F22 -> #REF! | K9: (賃金-雇用保険） | M9: 11 | N9: 41944
M10: 12 | N10: 41974
F11: =IF(ISERROR(VLOOKUP($B$24,#REF!,2,0))=TRUE,"",(VLOOKUP($B$24,#REF!,2,0))) | M11: 1 | N11: 42005
A12: =INDEX(#REF!, MATCH($B$26,#REF!,), MATCH("研究種別",#REF!,)) -> #REF! | C12: 賃金計算書 兼 支払決定書 | M12: 2 | N12: 42036
E13: 取引番号(伝票番号)： | M13: 3 | N13: 42064
E15: =" "&G2&H2&I2&J2&K2&" " -> 平成年月分 | M15: 41759 | N15: 41768
A16: 26首都大管理管臨第 | E16: 源泉徴収の有無： | F16: ★源泉徴収の有無を選択★ | M16: 41774 | N16: 41800
A17: した臨時職員について、右のとおり賃金の支払を決定する。 | E17: 雇用保険料の有無： | F17: ★雇用保険の有無を選択★ | G17: 入力用 | M17: 41789 | N17: 41800
A18: =H7 -> 0 | E18: 賃金単価（時給）： | F18: =#REF! -> #REF! | M18: 41803 | N18: 41830
A19: 理系管理課長 係長 担当者 | E19: 勤務時間数： | F19: =H4 -> 0 | M19: 41820 | N19: 41830
E20: 賃金支払額： | F20: =F18*F19 -> #REF! | M20: 41835 | N20: 41859
E21: 源泉徴収額： | F21: =IF(F16="有り（2ヶ月以内）",日額丙欄税額作業!B8,(IF(F16="無し（2ヶ月以内）",0,(IF(J9<88000,ROUNDDOWN(J9*3.063/100,),LOOKUP(J9,'月額表（平成27年1月以降分）'!$B$13:$B$347,'月額表（平成27年1月以降分）'!$L$13:$L$347)))))) -> #REF! | M21: 41850 | N21: 41859
E22: 雇用保険額： | F22: =IF(F17="有り",ROUNDDOWN(($F$20+$F$24)*5/1000,0),0) -> 0 | M22: 41866 | N22: 41892
A23: 会計年度 | B23: H26 | E23: 差引支給額： | F23: =F20-F22-F21 -> #REF! | M23: 41880 | N23: 41892
A24: 執行管理単位 | B24: =#REF! -> #REF! | E24: 通勤手当： | F24: =H3*H5*2 -> 0
A25: 所属（コース名） | B25: =#REF! -> #REF! | E25: 総支給額： | F25: =F23+F24 -> #REF! | M25: 41894 | N25: 41922
A26: 予算詳細コード | B26: =#REF! -> #REF! | C26: =#REF! -> #REF! | D26: =#REF! -> #REF! | M26: 41912 | N26: 41922
A27: 研究種別 | B27: =INDEX(#REF!, MATCH($B$26,#REF!,), MATCH("研究種別",#REF!,)) -> #REF! | E27: 通勤費用(往復) | F27: =H3*2 -> 0 | M27: 41927 | N27: 41953
A28: 研究代表者 | B28: =INDEX(#REF!, MATCH($B$26,#REF!,), MATCH("研究代表者",#REF!,)) -> #REF! | E28: 勤務日数 | F28: =H5 -> 0 | M28: 41942 | N28: 41953
A29: 担当者氏名 | B29: =#REF! -> #REF! | M29: 41957 | N29: 41983
A30: 区分 | B30: =#REF! -> #REF! | C30: =#REF! -> #REF! | D30: =#REF! -> #REF! | M30: 41971 | N30: 41983
A31: 業務内容 | B31: =#REF! -> #REF! | C31: =#REF! -> #REF! | D31: =#REF! -> #REF! | M31: 41985 | N31: 42013
A32: 契約件名 | B32: =B25 -> #REF! | E32: =#REF! -> #REF! | F32: ="・"&J2&"月分・理系）" -> ・月分・理系） | M32: 41992 | N32: 42013
E33: =#REF! -> #REF! | M33: 42019 | N33: 42045
A34: 伝票日付 | B34: =H7 -> 0 | E34: 雇用開始日 | F34: =#REF! -> #REF! | M34: 42034 | N34: 42045
E35: 雇用最終日 | F35: =#REF! -> #REF! | M35: 42048 | N35: 42073
A36: 契約日 | B36: =H6 -> #N/A | M36: 42062 | N36: 42073
M37: 42076 | N37: 42104
A38: 受入期日 | B38: =B34 -> 0 | E38: 支払予定日 | F38: =H8 -> 0 | M38: 42093 | N38: 42104
M39: 42109 | N39: 42132
A40: 氏名 | B40: =#REF! -> #REF! | C40: =#REF! -> #REF! | D40: =#REF! -> #REF! | M40: 42124 | N40: 42132
E41: 支払予定日(源泉分) | F41: =H9 -> #N/A
B42: =#REF! -> #REF! | C42: =#REF! -> #REF! | D42: =#REF! -> #REF!
A44: 債主ｺｰﾄﾞ | B44: =#REF! -> #REF!
E45: 受入備考(コード) | F45: =IF(F16="無し（2ヶ月以内）","1000000430",IF(F16="有り（2ヶ月以内）","1000000430",IF(F16="有り（3ヶ月以上）","1000000410",))) -> 0
A46: 個別支払 | B46: =IF(F16="有り（3ヶ月以上）","個別支払チェック有り",IF(F16="有り（2ヶ月以内）","個別支払チェック有り",(IF(F16="無し（2ヶ月以内）","個別支払チェック無し"," ")))) | E46: 受入備考(表示) | F46: =IF(F16="無し（2ヶ月以内）","日額丙（アルバイト等）",IF(F16="有り（2ヶ月以内）","日額丙（アルバイト等）",IF(F16="有り（3ヶ月以上）","月額乙（アルバイト等）",))) -> 0
B47: 差引支給額 | C47: 源泉徴収額 | E47: 雇用保険額 | F47: 通勤手当
A48: 業務内容 | B48: 201： 給与 | C48: 201： 給与 | E48: 201： 給与 | F48: 201： 給与
A50: 負担部門 | B50: =INDEX(#REF!, MATCH($B$26,#REF!,), MATCH("負担部門ｺｰﾄﾞ",#REF!,)) -> #REF!
A51: 予算科目 | B51: =INDEX(#REF!, MATCH($B$26,#REF!,), MATCH("予算科目ｺｰﾄﾞ",#REF!,)) -> #REF!
A52: 予算詳細 | B52: =C26 -> #REF!
A53: 財源 | B53: =INDEX(#REF!, MATCH($B$26,#REF!,), MATCH("財源",#REF!,)) -> #REF!
A54: 業務区分 | B54: =INDEX(#REF!, MATCH($B$26,#REF!,), MATCH("業務区分（賃金）",#REF!,)) -> #REF!
A55: 適用・項 | B55: 640： 費用（人件費） | C55: 42： 預り金人件費 | E55: 42： 預り金人件費 | F55: 640： 費用（人件費）
A56: 適用・目 | B56: 64090： アルバイト | C56: 42050： 預り金（所得税） | E56: 42100： 預り金（雇用保険） | F56: 64061：通勤手当（非職員）
A57: 作業場所 | B57: =INDEX(#REF!, MATCH($B$26,#REF!,), MATCH("コース名",#REF!,)) -> #REF!
A58: 金額 | B58: =F23 -> #REF! | C58: =F21 -> #REF! | E58: =F22 -> 0 | F58: =F24 -> 0
A60: 課税区分 | B60: 不課税 | C60: 不課税 | E60: 不課税 | F60: 課税
A62: [借]勘定科目 | B62: =INDEX(#REF!, MATCH($B$26,#REF!,), MATCH("借勘定（賃金）",#REF!,)) -> #REF! | C62: =INDEX(#REF!, MATCH($B$26,#REF!,), MATCH("借勘定（賃金）",#REF!,)) -> #REF! | D62: =INDEX(#REF!, MATCH($B$26,#REF!,), MATCH("借勘定（賃金）",#REF!,)) -> #REF! | E62: =INDEX(#REF!, MATCH($B$26,#REF!,), MATCH("借勘定（賃金）",#REF!,)) -> #REF! | F62: =INDEX(#REF!, MATCH($B$26,#REF!,), MATCH("通勤手当（借方）",#REF!,)) -> #REF!
B63: 85 ： 非・不課税 | C63: 85 ： 非・不課税 | E63: 85 ： 非・不課税 | F63: ★課税の種類を選択★
A64: [貸]勘定科目 | B64: =INDEX(#REF!, MATCH($B$26,#REF!,), MATCH("貸勘定（賃金）",#REF!,)) -> #REF! | C64: 41515：預り金 | E64: 41520：預り金 | F64: =INDEX(#REF!, MATCH($B$26,#REF!,), MATCH("貸勘定（賃金）",#REF!,)) -> #REF!
C65: （人件費・所得税） | E65: （人件費・雇用保険）
B66: 00 ： 対象外 | C66: 00 ： 対象外 | E66: 00 ： 対象外 | F66: 00 ： 対象外
F67: ※出納チェックを外して下さい。
F69: □賃金・報酬データ
F70: □コース送付済み
F71: □会計管理課完了
F73: [源泉徴収]
F74: ★源泉徴収の有無を選択★
F75: 無し（2ヶ月以内）
F76: 有り（2ヶ月以内）
F77: 有り（3ヶ月以上）
F79: [雇用保険料]
F80: ★雇用保険の有無を選択★
F81: 無し
... F87: 50:課税

Sheet 支給明細書　財務会計支払 
A1: 賃 金 支 給 明 細 書
A3: 所属 | C3: ='事務室処理用 財務会計支払'!B25 -> #REF!
A4: 担当教員 | C4: ='事務室処理用 財務会計支払'!B29 -> #REF!
A6: （カナ） | C6: ='事務室処理用 財務会計支払'!B42 -> #REF!
A7: 氏名 | C7: ='事務室処理用 財務会計支払'!B40 -> #REF!
A9: 対象期間 | C9: ='事務室処理用 財務会計支払'!E15 -> 平成年月分
A10: 賃金 | C10: ='事務室処理用 財務会計支払'!F20 -> #REF!
C11: 時給 | D11: ='事務室処理用 財務会計支払'!F18 -> #REF! | E11: 勤務時間数 | F11: ='事務室処理用 財務会計支払'!F19 -> 0
A12: 通勤手当 | C12: ='事務室処理用 財務会計支払'!F24 -> 0
C13: 通勤費用 （１日往復） | D13: ='事務室処理用 財務会計支払'!F27 -> 0 | E13: 勤務日数 | F13: ='事務室処理用 財務会計支払'!F28 -> 0
A14: 支給金額計 | C14: =C10+C12 -> #REF!
A16: 控除額 | B16: 雇用保険料 | C16: ='事務室処理用 財務会計支払'!F22 -> 0
B17: 所得税 | C17: ='事務室処理用 財務会計支払'!F21 -> #REF!
A18: 控除金額計 | C18: =C16+C17 -> #REF!
A20: 差引支給額 | C20: ='事務室処理用 財務会計支払'!F25 -> #REF!
A21: 口座振込額 | C21: ='事務室処理用 財務会計支払'!F25 -> #REF!
A22: 支給年月日 | C22: ='事務室処理用 財務会計支払'!F38 -> 0
A24: 上記の金額を支給する。
C28: （お問い合せ先）
C29: 首都大学東京管理部理系管理課
C30: 電話：042-677-2692（庶務係），2443（会計係）
F33: 都市教養学部（理系）
F34: ='事務室処理用 財務会計支払'!B26 -> #REF!
A35: 賃 金 支 給 明 細 書 | E35: 支給日： | F35: =C22 -> 0
E36: =C9 -> 平成年月分
A37: 所属 | C37: =C3 -> #REF!
A38: 担当教員 | C38: =C4 -> #REF!
A39: （カナ） | C39: =C6 -> #REF!
A40: 氏名 | C40: =C7 -> #REF!
A41: ※※※※※※※※※※※※※※※※※※※※※※※※※※※※※※※※※※※※※※※※※※※※※※※※※※※※※※※※※※※※※※※※※※※※※※※※※※※※※※※※※※※※※※※※※※
A42: ※※※※※※※※※※※※※※※※※※※※※※※※※※※※※※※※※※※※※※※※※※※※※※※※※※※※※※※※※※※※※※※※※※※※※※※※※※※※※※※※※※※※※※※※※※
A43: ※※※※※※※※※※※※※※※※※※※※※※※※※※※※※※※※※※※※※※※※※※※※※※※※※※※※※※※※※※※※※※※※※※※※※※※※※※※※※※※※※※※※※※※※※※
A44: ※※※※※※※※※※※※※※※※※※※※※※※※※※※※※※※※※※※※※※※※※※※※※※※※※※※※※※※※※※※※※※※※※※※※※※※※※※※※※※※※※※※※※※※※※※
A45: ※※※※※※※※※※※※※※※※※※※※※※※※※※※※※※※※※※※※※※※※※※※※※※※※※※※※※※※※※※※※※※※※※※※※※※※※※※※※※※※※※※※※※※※※※※
A46: ※※※※※※※※※※※※※※※※※※※※※※※※※※※※※※※※※※※※※※※※※※※※※※※※※※※※※※※※※※※※※※※※※※※※※※※※※※※※※※※※※※※※※※※※※※
A47: ※※※※※※※※※※※※※※※※※※※※※※※※※※※※※※※※※※※※※※※※※※※※※※※※※※※※※※※※※※※※※※※※※※※※※※※※※※※※※※※※※※※※※※※※※※
A48: ※※※※※※※※※※※※※※※※※※※※※※※※※※※※※※※※※※※※※※※※※※※※※※※※※※※※※※※※※※※※※※※※※※※※※※※※※※※※※※※※※※※※※※※※※※
A49: ※※※※※※※※※※※※※※※※※※※※※※※※※※※※※※※※※※※※※※※※※※※※※※※※※※※※※※※※※※※※※※※※※※※※※※※※※※※※※※※※※※※※※※※※※※
A50: ※※※※※※※※※※※※※※※※※※※※※※※※※※※※※※※※※※※※※※※※※※※※※※※※※※※※※※※※※※※※※※※※※※※※※※※※※※※※※※※※※※※※※※※※※※
A51: ※※※※※※※※※※※※※※※※※※※※※※※※※※※※※※※※※※※※※※※※※※※※※※※※※※※※※※※※※※※※※※※※※※※※※※※※※※※※※※※※※※※※※※※※※※
A52: ※※※※※※※※※※※※※※※※※※※※※※※※※※※※※※※※※※※※※※※※※※※※※※※※※※※※※※※※※※※※※※※※※※※※※※※※※※※※※※※※※※※※※※※※※※
... A63: ※※※※※※※※※※※※※※※※※※※※※※※※※※※※※※※※※※※※※※※※※※※※※※※※※※※※※※※※※※※※※※※※※※※※※※※※※※※※※※※※※※※※※※※※※※

Sheet 事務室処理用　科研費支払
F1: =IF(ISERROR(VLOOKUP($B$5,#REF!,2,0))=TRUE,"",(VLOOKUP($B$5,#REF!,2,0)))
A2: 支出負担行為決定書兼購入等依頼書（科研費・賃金専用）
A4: 平成２６年度 | D4: 発行番号
A5: 予算執行単位 | B5: =#REF! -> #REF! | C5: 決定区分 | D5: 契約 ・資金前渡 ・立替払い
A6: 所属（コース名） | B6: =INDEX(#REF!, MATCH($E$6,#REF!,), MATCH("コース名",#REF!,)) -> #REF! | C6: =INDEX(#REF!, MATCH(#REF!,#REF!,), MATCH("コース名",#REF!,)) -> #REF! | D6: 第１管理単位 | E6: =#REF! -> #REF!
A7: 職 | B7: ★職を選択★ | F7: ）
A8: 研究代表者 | B8: =INDEX(#REF!, MATCH($E$6,#REF!,), MATCH("研究代表者",#REF!,)) -> #REF! | C8: =INDEX(#REF!, MATCH($B$18,#REF!,), MATCH("研究代表者",#REF!,)) -> #REF!
A9: 研究課題名 | B9: =#REF! -> #REF!
A10: 件名 | B10: 賃金の支出
A11: 研究種別 | B11: =INDEX(#REF!, MATCH($E$6,#REF!,), MATCH("予算詳細名",#REF!,)) -> #REF!
A12: 執行科目 | B12: 謝金等
A13: 取引区分 | B13: 口座振込（賃金）
A14: 〔雇用内容〕 | C14: 支出予定年月日
A15: 区分 | B15: =#REF! -> #REF! | C15: 臨時職員名 | D15: =#REF! -> #REF! | E15: （コード） | F15: =B19 -> #REF!
A16: 業務内容 | B16: =#REF! -> #REF!
A17: (ﾌﾘｶﾞﾅ) 氏名 | B17: =#REF! -> #REF! | C17: 〔賃金の支払〕 | D17: 平成 ２６ 年 月分
B18: =#REF! -> #REF! | C18: 源泉徴収の有無 | E18: ★源泉徴収の有無を選択★
A19: 学修番号/債主ﾏｽﾀｺｰﾄﾞ | B19: =#REF! -> #REF! | C19: 雇用保険の有無 | E19: ★雇用保険の有無を選択★
A20: 雇用開始日 | B20: =#REF! -> #REF! | C20: 賃金単価（時給） | E20: =#REF! -> #REF!
A21: 雇用最終日 | B21: =#REF! -> #REF! | C21: 勤務時間数
A22: 勤務日数 | B22: =#REF! -> #REF! | C22: 賃金支払額 | E22: =E20*E21 -> #REF! | F22: 0 | G22: =IF(E18="有り（2ヶ月以内）","←日額丙欄税額作業シートで計算・確認","")
A23: 勤務時間 | B23: =B55&B56 -> #REF! | C23: 源泉徴収額 | E23: =IF(E18="有り（2ヶ月以内）"," ",(IF(E18="無し（2ヶ月以内）",0,(IF(B27<88000,ROUNDDOWN(B27*3.063/100,),LOOKUP(B27,'月額表（平成27年1月以降分）'!$B$13:$B$347,'月額表（平成27年1月以降分）'!$L$13:$L$347)))))) -> #REF!
C24: 雇用保険額 | E24: =IF(E19="有り",ROUNDDOWN((E22+E27)*5/1000,0),0) -> 0
C25: 通勤手当（1日・片道分）
C26: 勤務日数
B27: =E22-E24 -> #REF! | C27: 通勤手当 | E27: =E25*E26*2 -> 0
C28: 本人支払額 | E28: =E22-E23-E24+E27 -> #REF!
C30: 26首都大管理管臨第 | E30: 号により雇用した臨時職員に
B31: ついて、上記のとおり賃金の支払いを決定する。
C32: 平成 年 月 日
D34: 決 定 者
C35: 課長 | D35: 調査（係長） | E35: 担当者
E38: □賃金・報酬データ
E39: □コース送付済み
E40: □会計管理課完了
A42: 賃金
A43: [区分] | B43: [賃金単価] | D43: [職] | F43: [源泉徴収]
A44: 例：3-B | B44: 3000 | D44: 教授 | F44: ★源泉徴収の有無を選択★
A45: 1 | B45: 9999999999 | D45: 准教授 | F45: 無し（2ヶ月以内）
A46: 2 | B46: 9999999999 | D46: 助教 | F46: 有り（2ヶ月以内）
A47: 3-A | B47: 9999999999 | D47: 特任教員（ | F47: 有り（3ヶ月以上）
A48: 3-B | B48: 9999999999 | D48: 客員教員（
A49: 3-C | B49: 9999999999 | D49: リサーチアシスタント（ | F49: [雇用保険]
A50: 4 | B50: 9999999999 | D50: 特別研究員 | F50: ★雇用保険の有無を選択★
A51: 5 | B51: 9999999999 | D51: ★職を選択★ | F51: 無し
A52: ★区分を選択してください★ | B52: 9999999999 | F52: 有り
A55: =#REF! -> #REF! | B55: =A55 -> #REF!
A56: =#REF! -> #REF! | B56: =A56 -> #REF!

Sheet 支給明細書　科研費支払
A1: 賃 金 支 給 明 細 書
A3: 所属 | C3: ='事務室処理用 科研費支払'!B6 -> #REF!
A4: 担当教員 | C4: =#REF! -> #REF!
A6: （カナ） | C6: ='事務室処理用 科研費支払'!B17 -> #REF!
A7: 氏名 | C7: ='事務室処理用 科研費支払'!B18 -> #REF!
A9: 対象期間 | C9: ='事務室処理用 科研費支払'!D17 -> 平成 ２６ 年 月分
A10: 賃金 | C10: ='事務室処理用 科研費支払'!E22 -> #REF!
C11: 時給 | D11: ='事務室処理用 科研費支払'!E20 -> #REF! | E11: 勤務時間数 | F11: ='事務室処理用 科研費支払'!E21 -> 0
A12: 通勤手当 | C12: ='事務室処理用 科研費支払'!E27 -> 0
C13: 通勤費用 （１日往復） | D13: ='事務室処理用 科研費支払'!E25 -> 0 | E13: 勤務日数 | F13: ='事務室処理用 科研費支払'!E26 -> 0
A14: 支給金額計 | C14: =C10+C12 -> #REF!
A16: 控除額 | B16: 雇用保険料 | C16: ='事務室処理用 科研費支払'!E24 -> 0
B17: 所得税 | C17: ='事務室処理用 科研費支払'!E23 -> #REF!
A18: 控除金額計 | C18: ='事務室処理用 科研費支払'!E28 -> #REF!
A20: 差引支給額 | C20: ='事務室処理用 科研費支払'!E28 -> #REF!
A21: 口座振込額 | C21: =C20 -> #REF!
A22: 支給年月日 | C22: ='事務室処理用 科研費支払'!D14 -> 0
A24: 上記の金額を支給する。
C28: （お問い合せ先）
C29: 首都大学東京管理部理系管理課
C30: 電話：042-677-2692（庶務係），2443（会計係）
F33: 都市教養学部（理系）
F34: ='事務室処理用 科研費支払'!E6 -> #REF!
A35: 賃 金 支 給 明 細 書 | E35: 支給日： | F35: =C22 -> 0
E36: =C9 -> 平成 ２６ 年 月分
A37: 所属 | C37: =C3 -> #REF!
A38: 担当教員 | C38: =C4 -> #REF!
A39: （カナ） | C39: =C6 -> #REF!
A40: 氏名 | C40: =C7 -> #REF!
A41: ※※※※※※※※※※※※※※※※※※※※※※※※※※※※※※※※※※※※※※※※※※※※※※※※※※※※※※※※※※※※※※※※※※※※※※※※※※※※※※※※※※※※※※※※※※
A42: ※※※※※※※※※※※※※※※※※※※※※※※※※※※※※※※※※※※※※※※※※※※※※※※※※※※※※※※※※※※※※※※※※※※※※※※※※※※※※※※※※※※※※※※※※※
A43: ※※※※※※※※※※※※※※※※※※※※※※※※※※※※※※※※※※※※※※※※※※※※※※※※※※※※※※※※※※※※※※※※※※※※※※※※※※※※※※※※※※※※※※※※※※
A44: ※※※※※※※※※※※※※※※※※※※※※※※※※※※※※※※※※※※※※※※※※※※※※※※※※※※※※※※※※※※※※※※※※※※※※※※※※※※※※※※※※※※※※※※※※※
A45: ※※※※※※※※※※※※※※※※※※※※※※※※※※※※※※※※※※※※※※※※※※※※※※※※※※※※※※※※※※※※※※※※※※※※※※※※※※※※※※※※※※※※※※※※※※
A46: ※※※※※※※※※※※※※※※※※※※※※※※※※※※※※※※※※※※※※※※※※※※※※※※※※※※※※※※※※※※※※※※※※※※※※※※※※※※※※※※※※※※※※※※※※※
A47: ※※※※※※※※※※※※※※※※※※※※※※※※※※※※※※※※※※※※※※※※※※※※※※※※※※※※※※※※※※※※※※※※※※※※※※※※※※※※※※※※※※※※※※※※※※
A48: ※※※※※※※※※※※※※※※※※※※※※※※※※※※※※※※※※※※※※※※※※※※※※※※※※※※※※※※※※※※※※※※※※※※※※※※※※※※※※※※※※※※※※※※※※※
A49: ※※※※※※※※※※※※※※※※※※※※※※※※※※※※※※※※※※※※※※※※※※※※※※※※※※※※※※※※※※※※※※※※※※※※※※※※※※※※※※※※※※※※※※※※※※
A50: ※※※※※※※※※※※※※※※※※※※※※※※※※※※※※※※※※※※※※※※※※※※※※※※※※※※※※※※※※※※※※※※※※※※※※※※※※※※※※※※※※※※※※※※※※※
A51: ※※※※※※※※※※※※※※※※※※※※※※※※※※※※※※※※※※※※※※※※※※※※※※※※※※※※※※※※※※※※※※※※※※※※※※※※※※※※※※※※※※※※※※※※※※
A52: ※※※※※※※※※※※※※※※※※※※※※※※※※※※※※※※※※※※※※※※※※※※※※※※※※※※※※※※※※※※※※※※※※※※※※※※※※※※※※※※※※※※※※※※※※※
... A63: ※※※※※※※※※※※※※※※※※※※※※※※※※※※※※※※※※※※※※※※※※※※※※※※※※※※※※※※※※※※※※※※※※※※※※※※※※※※※※※※※※※※※※※※※※※

Sheet 日額丙欄税額作業
A1: 暫定的計算シート
A3: 本来、「日額丙欄適用」の場合は,日々の税額計算を行い、その合計額を控除する必要がある。
A4: ただし、平成24年度現在、法人の臨時職員賃金雇用制度では、①超過勤務なし、②1時間未満の端数勤務なし、
A5: であるため、課税となるのは、「単価1,240円×7時間45分=9,610円」の場合のみである。(理系エリアで通常想定される単価設定)
A6: そのため、暫定的にその日数を計上すれば、控除額の自動計算ができる。
B8: =E8*F10 -> 65 | D8: 税額単価 | E8: 13
B10: 実績で、 単価1,2４0円×7時間45分=9,610円 となっている日数を入れること。 | F10: 5
E11: →

Sheet 入力用　外国人雇用状況届出書
AG1: （日本工業規格Ａ列４）
B4: 様式第３号（第１０条関係）（表面）
B6: 雇 入 れ
B8: 離 職 | U8: に係る | Z8: 外国人雇用状況届出書
B11: フリガナ（カタカナ）
B12: ①外国人の氏名 （ローマ字又は漢字） | L12: 姓 | W12: 名 | AH12: ミドルネーム
B16: ②①の者の在留資格 | W16: ③①の者の在留期間（期限） （西暦）
AI18: 年 | AM18: 月 | AP18: 日
AO20: まで
B21: ④①の者の生年月日 （西暦） | W21: ⑤①の者の性別
AG22: １ 男 | AK22: ・ | AM22: ２ 女
N23: 年 | R23: 月 | U23: 日
B26: ⑥①の者の国籍 | W26: ⑦①の者の資格外 活動許可の有無
AG27: １ 有 | AK27: ・ | AM27: ２ 無
B32: 雇入れ年月日 （西暦） | N32: 年 | R32: 月 | V32: 日 | W32: 離職年月日 （西暦） | AI32: 年 | AM32: 月 | AQ32: 日
N35: 年 | R35: 月 | V35: 日 | AI35: 年 | AM35: 月 | AQ35: 日
N38: 年 | R38: 月 | V38: 日 | AI38: 年 | AM38: 月 | AQ38: 日
B42: 雇用対策法施行規則第10条第3項・整備省令附則第2条 の規定により上記のとおり届けます。
Y44: 平成 | AE44: 年 | AI44: 月 | AM44: 日
B47: 事業主 | F47: 事業所の名称、所在地、電話番号等
O48: 雇入れ又は離職に係る事業所 | AD48: 雇用保険適用事業所番号
AD49: 1 | AE49: 3 | AF49: 1 | AG49: 4 | AH49: - | AI49: 3 | AJ49: 0 | AK49: 7 | AL49: 4 | AM49: 9 | AN49: 9 | AO49: - | AP49: 7
O51: （名称） | S51: 公立大学法人首都大学東京 | AK51: ①の者が主として左記以外 の事業所で就労する場合
O53: （所在地）
AE54: ＴＥＬ
O55: 主たる事務所
O56: （名称）
O58: （所在地）
AE59: ＴＥＬ
F60: 氏名
Q62: 学 長 上野 淳 | AM62: 印
AF66: 公共職業安定所長 殿
A69: 様式第３号（裏面）
A71: 注意
B72: １ | C72: 雇入れに係る外国人雇用状況届出書として使用する場合の注意
C73: (1) | D73: 表面標題中「離職」の文字及び「平成19年10月1日時点で現に雇い入れている者」の文字並びに表面下部の「整備省令附則第2条」の文字を抹消すること。
C75: (2) | D75: ①欄には、外国人の氏名を、姓、名、ミドルネームの順にローマ字又は漢字で記載し、フリガナをカタカナで記載すること。（ミドルネームがない場合は姓名のみ記載）
C77: (3) | D77: ④欄には、①の者の生年月日を西暦で記載すること。
C78: (3) | D78: ②～④、⑥欄には、該当事項を記載すること。
C79: (4) | D79: ⑤欄には、①の者の性別について、該当するものの番号を○で囲むこと。
C80: (5) | D80: ⑦欄には、①の者が資格外活動の許可（出入国管理及び難民認定法第19条第2項の許可）を受けるべき者（「留学」、「就学」の在留資格の者等）である場合に、当該許可の有無について、該当するものの番号を○で囲むこと。
C83: (6) | D83: 表面中部に雇入れ年月日を記載すること。
B85: ２ | C85: 離職に係る外国人雇用状況届出書として使用する場合の注意
C86: (1) | D86: 表面標題中「雇入れ」の文字及び「平成19年10月1日時点で現に雇い入れている者」の文字並びに表面下部の「整備省令附則第2条」の文字を抹消すること。
C89: (2) | D89: ①～⑥欄について、１と同様とすること。
C91: (3) | D91: ⑦欄は記載不要であること。
C93: (4) | D93: 表面中部に離職年月日を記載すること。
B95: ３ | C95: 雇入れ及び離職の双方に係る外国人雇用状況届出書として使用する場合の注意
C96: (1) | D96: 表面標題中「平成19年10月1日時点で現に雇い入れている者」の文字及び表面下部の「整備省令附則第2条」の文字を抹消すること。
C99: (2) | D99: ①～⑦欄について、１と同様とすること。
C101: (3) | D101: 表面中部に雇入れ年月日及び離職年月日を記載すること。
C103: (4) | D103: その他１及び２に従うこと。
B105: ４ | C105: 平成19年10月1日時点で現に雇い入れている者に係る外国人雇用状況届出書として使用する場合の注意
C106: (1) | D106: 表面標題中「雇入れ」の文字及び「離職」の文字並びに表面下部の「雇用対策法施行規則第10条第3項」の文字を抹消すること。
C109: (2) | D109: ①～⑥欄について、１と同様とすること。
C111: (3) | D111: ⑦欄は記載不要であること。
C113: (4) | D113: 表面中部の雇入れ年月日及び離職年月日は記載不要であること。
C115: (5) | D115: 平成19年10月1日時点で現に雇い入れている者が、離職した場合には、２に従い記載すること。
B117: ５ | C117: 同一の者について、複数回にわたり雇入れ又は離職が生じた場合は、表面中部にそれぞれの雇入れ年月日又は離職年月日を記載すること。
B120: ６ | C120: この様式は、届出の対象となる外国人1人につき1枚を使用すること。
B122: ７ | C122: 表面の記載に当たっては、①～⑥欄については外国人登録証明書又は旅券、⑦欄については資格外活動許可書又は就労資格証明書により確認し、記載すること。
B125: ８ | C125: 事業所の名称、所在地、電話番号等欄には、雇入れ又は離職に係る事業所の名称、所在地、電話番号、雇用保険適用事業所番号並びに事業主が法人の場合は、法人の名称及びその主たる事務所の所在地、電話番号を記載すること。また、①の者が派遣労働者又は請負労働者として主として他の事業所で就労する場合は□にチェックすること。
B130: ９ | C130: 事業主の氏名（法人にあっては代表者の氏名）については、記名押印又は自筆による署名のいずれかにより記載すること。
B133: 10 | C133: 雇入れに係る届出にあっては、雇い入れた日の翌月の末日までに、離職に係る届出にあっては、離職した日の翌月の末日までに届け出ること。なお、届出の対象となる外国人が雇用保険の被保険者である場合の届出期限と異なるので注意すること。また、平成19年10月1日時点で現に雇い入れている者に係る届出にあっては、平成20年10月1日までに届け出ること。
B138: 11 | C138: 本届出は電子申請による手続も可能であること。
B140: 12 | C140: 表面下部の「整備省令」とは、「雇用対策法及び地域雇用開発促進法の一部を改正する法律の施行に伴う関係省令の整備等に関する省令（平成19年厚生労働省令第102号）」を表す。
